{"BaseModel.a5b6aeef-c29b-46c9-b390-0f87383fa80b": {"id": "a5b6aeef-c29b-46c9-b390-0f87383fa80b", "created_at": "2023-08-09T14:29:13.453274", "updated_at": "2023-08-09T14:29:13.453326", "name": "My_First_Model", "my_number": 89, "__class__": "BaseModel"}, "BaseModel.f3165c25-86aa-4198-8943-a656e1fe7df0": {"id": "f3165c25-86aa-4198-8943-a656e1fe7df0", "created_at": "2023-08-09T14:29:51.466148", "updated_at": "2023-08-09T14:29:51.466193", "name": "My_First_Model", "my_number": 89, "__class__": "BaseModel"}, "BaseModel.fff388f1-a687-4158-9c99-e0886d51c481": {"id": "fff388f1-a687-4158-9c99-e0886d51c481", "created_at": "2023-08-09T14:30:44.623566", "updated_at": "2023-08-09T14:30:44.623608", "name": "My_First_Model", "my_number": 89, "__class__": "BaseModel"}, "BaseModel.c8ffb1a7-3ae9-40dc-8388-ff2e7593cf7c": {"id": "c8ffb1a7-3ae9-40dc-8388-ff2e7593cf7c", "created_at": "2023-08-09T19:31:59.670365", "updated_at": "2023-08-09T19:31:59.670451", "name": "My_First_Model", "my_number": 89, "__class__": "BaseModel"}}